audax/__init__.py
audax/feature_helper.py
audax/commons/__init__.py
audax/commons/utils.py
audax/core/__init__.py
audax/core/functional.py
audax/core/helpers.py
audax/core/stft.py
audax/frontends/__init__.py
audax/frontends/leaf.py
audax/frontends/sincnet.py
audax/models/__init__.py
audax/models/classifier.py
audax/models/convnext.py
audax/models/efficientnet.py
audax/models/resnet.py
audax/models/utils.py
audax/models/layers/__init__.py
audax/models/layers/drop.py
audax/models/layers/efficientnet_helpers.py
audax/models/layers/mlp.py
audax/models/layers/similarity_layers.py
audax/training_utils/__init__.py
audax/training_utils/eval_supervised.py
audax/training_utils/metrics_helper.py
audax/training_utils/misc.py
audax/training_utils/train_contrastive.py
audax/training_utils/train_supervised.py
audax/training_utils/training_utilities.py
audax/training_utils/trainstate.py
audax/training_utils/data_v2/__init__.py
audax/training_utils/data_v2/dataset.py
audax/training_utils/data_v2/helpers.py
audax/training_utils/data_v2/torch_transforms.py
audax/training_utils/data_v2/transforms.py
audax/transforms/__init__.py
audax/transforms/mixup.py
audax/transforms/spec_augment.py
audax-0.0.3.dist-info/LICENSE
audax-0.0.3.dist-info/METADATA
audax-0.0.3.dist-info/WHEEL
audax-0.0.3.dist-info/top_level.txt
audax-0.0.3.dist-info/RECORD
