Metadata-Version: 2.1
Name: audax
Version: 0.0.3
Summary: audio ML for Jax
Home-page: https://github.com/SarthakYadav/audio_data_utils
Author: Sarthak Yadav
License: UNKNOWN
Platform: UNKNOWN
Requires-Python: >=3.8
License-File: LICENSE
